kade_drive/__init__.py
kade_drive/cli.py
kade_drive/client.py
kade_drive/core/__init__.py
kade_drive/core/config.py
kade_drive/core/crawling.py
kade_drive/core/network.py
kade_drive/core/node.py
kade_drive/core/protocol.py
kade_drive/core/routing.py
kade_drive/core/storage.py
kade_drive/core/utils.py
kade_drive/server.py
kade_drive/test_store_file.py
kade_drive/tests/__init__.py
kade_drive/tests/conftest.py
kade_drive/tests/data_to_split.txt
kade_drive/tests/test_node.py
kade_drive/tests/test_routing.py
kade_drive/tests/test_server.py
kade_drive/tests/test_splitdata.py
kade_drive/tests/test_storage.py
kade_drive/tests/test_utils.py
kade_drive-0.9.0.dist-info/LICENSE
kade_drive-0.9.0.dist-info/METADATA
kade_drive-0.9.0.dist-info/WHEEL
kade_drive-0.9.0.dist-info/entry_points.txt
kade_drive-0.9.0.dist-info/RECORD
