Metadata-Version: 2.1
Name: kade-drive
Version: 0.9.0
Summary: distributed file system based on kademlia dht
License: MIT
Author: DanielUH2019
Author-email: danielcardenascabrera2016@gmail.com
Requires-Python: >=3.10,<3.12
Classifier: License :: OSI Approved :: MIT License
Classifier: Programming Language :: Python :: 3
Classifier: Programming Language :: Python :: 3.10
Classifier: Programming Language :: Python :: 3.11
Requires-Dist: filelock (>=3.12.2,<4.0.0)
Requires-Dist: message-system (>=0.1.2,<0.2.0)
Requires-Dist: rpyc (==5.3.1)
Requires-Dist: typer (==0.9.0)
